{
    "res": {
        "1ED2E063": {
            "y": 0, 
            "x": 158, 
            "w": 71, 
            "h": 107
        }, 
        "A2F51345": {
            "y": 0, 
            "x": 0, 
            "w": 82, 
            "h": 108
        }, 
        "69F8B376": {
            "y": 108, 
            "x": 0, 
            "w": 79, 
            "h": 106
        }, 
        "1EA008F0": {
            "y": 0, 
            "x": 82, 
            "w": 76, 
            "h": 106
        }
    }, 
    "mc": {
        "body000_0_0r": {
            "frames": [
                {
                    "y": -107, 
                    "res": "1ED2E063", 
                    "x": -48
                }, 
                {
                    "y": -108, 
                    "res": "1EA008F0", 
                    "x": -47
                }, 
                {
                    "y": -107, 
                    "res": "A2F51345", 
                    "x": -47
                }, 
                {
                    "y": -108, 
                    "res": "69F8B376", 
                    "x": -49
                }
            ], 
            "frameRate": "8", 
            "events": []
        }
    }
}